{
	"name": "DelimitedText2",
	"properties": {
		"linkedServiceName": {
			"referenceName": "AzureBlobStorage1",
			"type": "LinkedServiceReference"
		},
		"annotations": [],
		"type": "DelimitedText",
		"typeProperties": {
			"location": {
				"type": "AzureBlobStorageLocation",
				"container": "container3110"
			},
			"columnDelimiter": ",",
			"escapeChar": "\\",
			"firstRowAsHeader": true,
			"quoteChar": "\""
		},
		"schema": [
			{
				"name": "dept_onshore",
				"type": "String"
			},
			{
				"name": "onshoreManager",
				"type": "String"
			},
			{
				"name": "Deptid",
				"type": "String"
			}
		]
	}
}